google_finance_scraper/__init__.py
google_finance_scraper/core.py
google_finance_scraper-1.0.0.dist-info/licenses/LICENSE
google_finance_scraper-1.0.0.dist-info/METADATA
google_finance_scraper-1.0.0.dist-info/WHEEL
google_finance_scraper-1.0.0.dist-info/top_level.txt
google_finance_scraper-1.0.0.dist-info/RECORD
