Metadata-Version: 2.4
Name: google-finance-scraper
Version: 1.0.0
Summary: Fast Google Finance scraper for stocks, forex, crypto with pandas output
Home-page: https://github.com/93627829939e93u3/google_finance_scraper.git
Author: Ganesh Raut
Author-email: Ganesh Raut <rautganesh9370@gmail.com>
License: MIT
Project-URL: Homepage, https://github.com/93627829939e93u3
Project-URL: Repository, https://github.com/93627829939e93u3/google_finance_scraper.git
Classifier: Programming Language :: Python :: 3
Classifier: License :: OSI Approved :: MIT License
Classifier: Operating System :: OS Independent
Requires-Python: >=3.8
License-File: LICENSE
Requires-Dist: aiohttp
Requires-Dist: beautifulsoup4
Requires-Dist: pandas
Dynamic: license-file
